{"nodes": [{"id": "iqvia_logo", "label": "IQVIA", "file_type": "image", "source_file": "public/logo/IQVIA.png", "source_location": null, "source_url": null, "captured_at": null, "author": null, "contributor": null}, {"id": "iqvia_organization", "label": "IQVIA Holdings", "file_type": "concept", "source_file": "public/logo/IQVIA.png", "source_location": null, "source_url": null, "captured_at": null, "author": null, "contributor": null}], "edges": [{"source": "iqvia_logo", "target": "iqvia_organization", "relation": "references", "confidence": "EXTRACTED", "confidence_score": 1.0, "source_file": "public/logo/IQVIA.png", "source_location": null, "weight": 1.0}, {"source": "iqvia_logo", "target": "logo_collection", "relation": "shares_data_with", "confidence": "INFERRED", "confidence_score": 0.9, "source_file": "public/logo/IQVIA.png", "source_location": null, "weight": 0.8}], "hyperedges": []}